aws_utils/__init__.py
aws_utils/aws_logger.py
aws_utils/kms_client.py
aws_utils/s3_client.py
aws_utils/secret_manager.py
aws_utils/sqs/__init__.py
aws_utils/sqs/consumer.py
aws_utils/sqs/producer.py
aws_utils/sqs/worker.py
learn_utils.aws_utils-1.0.13.dist-info/METADATA
learn_utils.aws_utils-1.0.13.dist-info/RECORD
learn_utils.aws_utils-1.0.13.dist-info/WHEEL
learn_utils.aws_utils-1.0.13.dist-info/top_level.txt
tasks/__init__.py
tasks/s3.py
