Metadata-Version: 2.1
Name: learn-utils.aws-utils
Version: 1.0.13
Summary: A collection of common aws code.
Home-page: UNKNOWN
Author: Luis Felipe Muller
Author-email: luisfmuller@gmail.com
License: UNKNOWN
Keywords: logger,boto3,sqs,s3
Platform: UNKNOWN
Requires-Dist: boto3 (==1.9.21)
Requires-Dist: botocore (==1.12.21)
Requires-Dist: certifi (>=2018.8.13)
Requires-Dist: chardet (==3.0.4)
Requires-Dist: docutils (==0.14)
Requires-Dist: idna (==2.7)
Requires-Dist: invoke (==1.2.0)
Requires-Dist: jmespath (==0.9.3)
Requires-Dist: requests (==2.19.1)
Requires-Dist: s3transfer (==0.1.13)
Requires-Dist: six (==1.11.0)
Requires-Dist: watchtower (==0.5.3)
Requires-Dist: urllib3 (==1.23); python_version < "4"
Requires-Dist: python-dateutil (==2.7.3); python_version >= "2.7"
